{
  "sections": {
    "main": {
      "type": "main-page",
      "settings": {
        "color_scheme": "accent-2",
        "padding_top": 56,
        "padding_bottom": 4
      }
    },
    "0b02a2cc-8135-4aa7-b403-579fe8d4b6d5": {
      "type": "custom-retail-locations-map",
      "settings": {
        "custom_liquid": "<iframe src=\"https:\/\/www.google.com\/maps\/d\/embed?mid=1cC5p1DXtt2nW73MTFY8CUMqoNhfzc6I&ehbc=2E312F\" width=\"100%\" height=\"480\"><\/iframe>",
        "color_scheme": "accent-2",
        "padding_top": 0,
        "padding_bottom": 44
      }
    },
    "b75c6231-13d4-477f-80c5-101e29f76c72": {
      "type": "custom-retail-locations-grid",
      "blocks": {
        "548e3305-b04f-4292-8221-722658e46e8e": {
          "type": "retail-location",
          "settings": {
            "image": "shopify:\/\/shop_images\/loadzatoys.jpg",
            "address": "Orchard Park Shopping Centre 2271 Harvey Avenue",
            "city": "Kelowna, BC V1Y 6H2",
            "url": "https:\/\/loadzatoyz.com\/"
          }
        },
        "95a629e9-814b-4769-bedd-97942b169e56": {
          "type": "retail-location",
          "settings": {
            "image": "shopify:\/\/shop_images\/vernon_teach_and_learn_logo-1920w.png",
            "address": "3015 30th Ave",
            "city": "Vernon, BC V1T 2C1",
            "url": "https:\/\/www.vernonteachandlearn.com\/"
          }
        },
        "558521dd-6f8b-455b-8759-a2bf8375b6d1": {
          "type": "retail-location",
          "settings": {
            "image": "shopify:\/\/shop_images\/rustic-refined-resized-logo_360x_852fbc7a-18b5-4a5d-b7f5-b048ea977c34.png",
            "address": "10109 Main St",
            "city": "Summerland, BC V0H 1Z2",
            "url": "https:\/\/rusticandrefined.ca\/"
          }
        },
        "f7f8c4e7-0569-4e7e-bd74-0623ad3a38a5": {
          "type": "retail-location",
          "settings": {
            "image": "shopify:\/\/shop_images\/rhymes-with-purple.png",
            "address": "#149 - 1151 10th Ave SW",
            "city": "Salmon Arm, BC V1E 1T3",
            "url": "https:\/\/rhymeswithpurple.ca\/"
          }
        },
        "896250a2-74e6-438c-938e-363bb1b95d87": {
          "type": "retail-location",
          "settings": {
            "image": "shopify:\/\/shop_images\/ogopogo.jpg",
            "address": "287b Bernard Ave",
            "city": "Kelowna, BC V1Y 6N2",
            "url": "https:\/\/www.ogopogogiftland.com\/"
          }
        },
        "901739ab-2a89-41bc-be26-53de1658a529": {
          "type": "retail-location",
          "settings": {
            "image": "shopify:\/\/shop_images\/quantum.jpg",
            "address": "#15 - 150 Hollywood Road S",
            "city": "Kelowna, BC V1X 3S9",
            "url": "https:\/\/www.quantumgames.ca\/"
          }
        },
        "18864822-77bf-4484-aacb-f68a7104063c": {
          "type": "retail-location",
          "settings": {
            "image": "shopify:\/\/shop_images\/canadian_handmade.png",
            "address": "450 Main St",
            "city": "Penticton, BC V2A 5C5",
            "url": "https:\/\/www.instagram.com\/canadianhandmadepenticton\/"
          }
        },
        "8d8c1ea5-0cfd-403b-b889-bc3f484974be": {
          "type": "retail-location",
          "settings": {
            "image": "shopify:\/\/shop_images\/baby_and_me_logo.jpg",
            "address": "2061 Harvey Ave",
            "city": "Kelowna, BC V1Y 8M1",
            "url": "https:\/\/www.babyandme.ca\/"
          }
        },
        "9dd63f7e-8e6e-4fe7-8a51-236513a01f7c": {
          "type": "retail-location",
          "settings": {
            "image": "shopify:\/\/shop_images\/globally-fair.png",
            "address": "#107 - 3001 Tutt St",
            "city": "Kelowna, BC V1Y 2H4",
            "url": "https:\/\/www.globallyfair.ca\/"
          }
        },
        "cbfbb911-bae7-4624-8dc1-9ff284f9a215": {
          "type": "retail-location",
          "settings": {
            "image": "shopify:\/\/shop_images\/ok-science-centre.png",
            "address": "2704 Highway 6",
            "city": "Vernon, BC V1T 5G5",
            "url": "https:\/\/okscience.ca\/"
          }
        },
        "52159c5f-322b-40b2-a33d-ff28393593b1": {
          "type": "retail-location",
          "settings": {
            "image": "shopify:\/\/shop_images\/once_upon_a_child_logo.png",
            "address": "1780 Baron Road",
            "city": "Kelowna, BC V1X 7G9",
            "url": "https:\/\/www.onceuponachild.com\/home"
          }
        },
        "bf1ab674-092c-4e9a-a9b9-1113027e15d7": {
          "type": "retail-location",
          "settings": {
            "image": "shopify:\/\/shop_images\/sylvan-learning.png",
            "address": "2065 Enterprise Way",
            "city": "Kelowna, BC V1Y 8R6",
            "url": "https:\/\/www.sylvanlearning.com\/"
          }
        },
        "b910bceb-9636-4e07-8684-99da17c4bd31": {
          "type": "retail-location",
          "settings": {
            "image": "shopify:\/\/shop_images\/odin-books.jpg",
            "address": "108 East Broadway",
            "city": "Vancouver, BC V5T 1V9",
            "url": "https:\/\/odinbooks.com\/"
          }
        },
        "250e6fca-af9b-4f3e-a7a6-cff698d3bd10": {
          "type": "retail-location",
          "settings": {
            "image": "shopify:\/\/shop_images\/tickleberrys.png",
            "address": "1207 Main St",
            "city": "Okanagan Falls, BC V0H 1R4",
            "url": "https:\/\/tickleberrys.com\/"
          }
        },
        "f3ced8d0-d345-4233-9f63-c7e7f23446b3": {
          "type": "retail-location",
          "settings": {
            "image": "shopify:\/\/shop_images\/log-barn.webp",
            "address": "4782 BC-97A",
            "city": "Armstrong, BC V0E 1B8",
            "url": "https:\/\/www.logbarn1912.ca\/"
          }
        },
        "12ff515e-164f-4c6a-8ea7-dabf6694c629": {
          "type": "retail-location",
          "settings": {
            "image": "shopify:\/\/shop_images\/little-earth-childrens-store.png",
            "address": "1020 Commercial Dr",
            "city": "Vancouver, BC V5L 3W9",
            "url": "https:\/\/littleearthvancouver.com\/"
          }
        },
        "861ffffd-a044-427f-a79c-63b62388f31f": {
          "type": "retail-location",
          "settings": {
            "image": "shopify:\/\/shop_images\/once-upon-a-child-victoria.png",
            "address": "1563 Pandora Ave",
            "city": "Victoria, BC V8R 6P9",
            "url": "https:\/\/www.onceuponachild.com\/locations\/victoria-bc"
          }
        },
        "040c7ac8-719d-4b19-bcb8-fad9721f0979": {
          "type": "retail-location",
          "settings": {
            "image": "shopify:\/\/shop_images\/armstrong-flower-gift.jpg",
            "address": "3105 Smith Dr",
            "city": "Armstrong, BC V0E 1B0",
            "url": "https:\/\/www.armstrongflowershop.com\/"
          }
        },
        "213fa52c-8500-411d-9af1-5caf88a5fb79": {
          "type": "retail-location",
          "settings": {
            "image": "shopify:\/\/shop_images\/home-cor.png",
            "address": "West Kelowna",
            "city": "Vintage View Center",
            "url": "https:\/\/homecor.ca\/"
          }
        },
        "62c15aeb-dfc9-49d3-9dd2-354f66947685": {
          "type": "retail-location",
          "settings": {
            "image": "shopify:\/\/shop_images\/Tumbleweed_Toys.png",
            "address": "1201 Summit Dr",
            "city": "Kamloops, BC V2C 6C5",
            "url": "https:\/\/www.tumbleweedtoys.ca\/"
          }
        },
        "0c272544-55cc-416c-9e9d-c77209443b4a": {
          "type": "retail-location",
          "settings": {
            "image": "shopify:\/\/shop_images\/tourism-kelowna.jpg",
            "address": "238 Queensway",
            "city": "Kelowna, BC V1Y 6S4",
            "url": "https:\/\/www.tourismkelowna.com\/plan\/visitor-centre\/"
          }
        },
        "3660dac9-bbc2-4982-888a-cf57ca1f3a74": {
          "type": "retail-location",
          "settings": {
            "image": "shopify:\/\/shop_images\/tickleberrys-downtown.jpg",
            "address": "202 Main St",
            "city": "Penticton, BC V2A 5B2",
            "url": "https:\/\/tickleberrys.com\/downtown-penticton\/"
          }
        },
        "57471167-8110-40d3-9eee-fa3e52037890": {
          "type": "retail-location",
          "settings": {
            "image": "shopify:\/\/shop_images\/lagoon-baby.webp",
            "address": "22770 Lougheed Hwy",
            "city": "Maple Ridge, BC V2X 2V6",
            "url": "https:\/\/www.lagoonbaby.com\/"
          }
        },
        "e0382f21-e6a4-4c95-812c-1b4dac0eec23": {
          "type": "retail-location",
          "settings": {
            "image": "shopify:\/\/shop_images\/camelot-kids.jpg",
            "address": "1496 Cartwright St",
            "city": "Vancouver, BC V6H 3Y5",
            "url": "https:\/\/camelotkids.com\/"
          }
        },
        "abb7afb2-e172-48fb-8943-73586d6233ee": {
          "type": "retail-location",
          "settings": {
            "image": "shopify:\/\/shop_images\/once-upon-coquitlam.jpg",
            "address": "1300 Woolridge St",
            "city": "Coquitlam, BC V3K 6Y6",
            "url": "https:\/\/www.onceuponachild.com\/locations\/coquitlam-bc"
          }
        },
        "45509cf1-a031-4096-a6d5-a45c29e1a46a": {
          "type": "retail-location",
          "settings": {
            "image": "shopify:\/\/shop_images\/once-upon-langley.jpg",
            "address": "#104 - 20121 Willowbrook Dr",
            "city": "Langley Township, BC V2Y 0L3",
            "url": ""
          }
        },
        "5109ba6d-4ba9-4f9f-89cf-8a8a354a7485": {
          "type": "retail-location",
          "settings": {
            "image": "shopify:\/\/shop_images\/play-it-again.jpg",
            "address": "458 Ward St",
            "city": "Nelson, BC V1L 1S8",
            "url": "https:\/\/www.playitagainkids.ca\/"
          }
        },
        "e5a35262-8fb2-45c6-8269-207591bbc79c": {
          "type": "retail-location",
          "settings": {
            "image": "shopify:\/\/shop_images\/grow-fernie.png",
            "address": "482 8 Ave",
            "city": "Fernie, BC V0B 1M0",
            "url": "https:\/\/www.growfernie.com\/"
          }
        },
        "e751e77a-8658-45f7-ae4c-8e7e76bc98e5": {
          "type": "retail-location",
          "settings": {
            "image": "shopify:\/\/shop_images\/on-alex.png",
            "address": "#1 - 250 Alexander St NE",
            "city": "Salmon Arm, BC V1E 1S9",
            "url": "https:\/\/on-alex.myshopify.com\/"
          }
        },
        "72302405-1116-4a33-98bb-01c9db877fc9": {
          "type": "retail-location",
          "settings": {
            "image": "shopify:\/\/shop_images\/buddies-toys_logo_260x_bc45598c-5cda-4d99-8825-4ccedaffddab.webp",
            "address": "2494 Beacon Ave",
            "city": "Sidney, BC V8L 1X8",
            "url": "https:\/\/buddiestoys.com\/"
          }
        },
        "d83a2b06-4f54-4b4e-b09c-04608f158724": {
          "type": "retail-location",
          "settings": {
            "image": "shopify:\/\/shop_images\/SputtergotchLogos001.jpg",
            "address": "113a Central Ave N",
            "city": "Swift Current, SK S9H 0K9",
            "url": "https:\/\/www.sputtergotchtoys.com\/"
          }
        },
        "c64c37eb-01fd-429f-9ee2-b4babce9ca7c": {
          "type": "retail-location",
          "settings": {
            "image": "shopify:\/\/shop_images\/WeeBee-Logo-2.jpg",
            "address": "492 Shoup Ave",
            "city": "Idaho Falls, ID 83402",
            "url": "http:\/\/www.weebeetoys.com\/"
          }
        },
        "af6118d2-e047-4f5b-af6d-a6250d8c8239": {
          "type": "retail-location",
          "settings": {
            "image": "shopify:\/\/shop_images\/cropped-logo-everythingbaby-trns.png",
            "address": "#102 - 770 Central St E",
            "city": "Prince George, BC V2M 3B7",
            "url": "https:\/\/www.everythingbaby.ca\/"
          }
        }
      },
      "block_order": [
        "548e3305-b04f-4292-8221-722658e46e8e",
        "95a629e9-814b-4769-bedd-97942b169e56",
        "558521dd-6f8b-455b-8759-a2bf8375b6d1",
        "f7f8c4e7-0569-4e7e-bd74-0623ad3a38a5",
        "896250a2-74e6-438c-938e-363bb1b95d87",
        "901739ab-2a89-41bc-be26-53de1658a529",
        "18864822-77bf-4484-aacb-f68a7104063c",
        "8d8c1ea5-0cfd-403b-b889-bc3f484974be",
        "9dd63f7e-8e6e-4fe7-8a51-236513a01f7c",
        "cbfbb911-bae7-4624-8dc1-9ff284f9a215",
        "52159c5f-322b-40b2-a33d-ff28393593b1",
        "bf1ab674-092c-4e9a-a9b9-1113027e15d7",
        "b910bceb-9636-4e07-8684-99da17c4bd31",
        "250e6fca-af9b-4f3e-a7a6-cff698d3bd10",
        "f3ced8d0-d345-4233-9f63-c7e7f23446b3",
        "12ff515e-164f-4c6a-8ea7-dabf6694c629",
        "861ffffd-a044-427f-a79c-63b62388f31f",
        "040c7ac8-719d-4b19-bcb8-fad9721f0979",
        "213fa52c-8500-411d-9af1-5caf88a5fb79",
        "62c15aeb-dfc9-49d3-9dd2-354f66947685",
        "0c272544-55cc-416c-9e9d-c77209443b4a",
        "3660dac9-bbc2-4982-888a-cf57ca1f3a74",
        "57471167-8110-40d3-9eee-fa3e52037890",
        "e0382f21-e6a4-4c95-812c-1b4dac0eec23",
        "abb7afb2-e172-48fb-8943-73586d6233ee",
        "45509cf1-a031-4096-a6d5-a45c29e1a46a",
        "5109ba6d-4ba9-4f9f-89cf-8a8a354a7485",
        "e5a35262-8fb2-45c6-8269-207591bbc79c",
        "e751e77a-8658-45f7-ae4c-8e7e76bc98e5",
        "72302405-1116-4a33-98bb-01c9db877fc9",
        "d83a2b06-4f54-4b4e-b09c-04608f158724",
        "c64c37eb-01fd-429f-9ee2-b4babce9ca7c",
        "af6118d2-e047-4f5b-af6d-a6250d8c8239"
      ],
      "settings": {
        "color_scheme": "accent-2",
        "padding_top": 0,
        "padding_bottom": 36
      }
    }
  },
  "order": [
    "main",
    "0b02a2cc-8135-4aa7-b403-579fe8d4b6d5",
    "b75c6231-13d4-477f-80c5-101e29f76c72"
  ]
}
